django_encrypted_fields_and_files-0.1.12.dist-info/licenses/LICENSE
encrypted_fields/__init__.py
encrypted_fields/encrypted_field_mixin.py
encrypted_fields/encrypted_fields.py
encrypted_fields/encrypted_file_mixin.py
encrypted_fields/encrypted_files.py
serve_files/__init__.py
serve_files/admin.py
serve_files/apps.py
serve_files/examples.py
serve_files/models.py
serve_files/tests.py
serve_files/urls.py
serve_files/views.py
serve_files/migrations/__init__.py
django_encrypted_fields_and_files-0.1.12.dist-info/METADATA
django_encrypted_fields_and_files-0.1.12.dist-info/WHEEL
django_encrypted_fields_and_files-0.1.12.dist-info/top_level.txt
django_encrypted_fields_and_files-0.1.12.dist-info/RECORD
