Metadata-Version: 2.4
Name: django-encrypted-fields-and-files
Version: 0.1.12
Summary: Campos e storages criptografados para o Django com suporte a timestamp para evitar cache.
Home-page: https://github.com/D3NKYT0/django-encrypted-fields
Author: Denky
Author-email: Denky <contato@denky.dev.br>
Maintainer-email: Denky <contato@denky.dev.br>
License: MIT
Project-URL: Homepage, https://denky.dev.br/django-encrypted-fields
Project-URL: Documentation, https://github.com/D3NKYT0/django-encrypted-fields/wiki
Project-URL: Repository, https://github.com/D3NKYT0/django-encrypted-fields
Project-URL: Issue Tracker, https://github.com/D3NKYT0/django-encrypted-fields/issues
Keywords: django,encryption,fields,files,timestamp,cache
Classifier: Framework :: Django
Classifier: Programming Language :: Python
Classifier: License :: OSI Approved :: MIT License
Classifier: Development Status :: 4 - Beta
Classifier: Intended Audience :: Developers
Classifier: Topic :: Software Development :: Libraries :: Python Modules
Classifier: Topic :: Security :: Cryptography
Requires-Python: >=3.10
License-File: LICENSE
Requires-Dist: Django>=4.2
Requires-Dist: cryptography<45.0.0,>=41.0.5
Requires-Dist: pillow>=10.0.0
Dynamic: author
Dynamic: home-page
Dynamic: license-file
Dynamic: requires-python
